{
  "appId": "54486769",
  "entryUrl": "https://serpmonn.ru/frontend/mini/miniapp.html",
  "title": "Серпмонн",
  "tagline": "Агентный поиск, новости, инструменты и свои игры — внутри ВКонтакте",
  "nav": {
    "profile": "Профиль",
    "search": "Поиск",
    "news": "База",
    "tools": "Инструменты",
    "games": "Игры"
  },
  "profile": {
    "title": "Профиль",
    "guestName": "Гость",
    "guestText": "Вход выполняется автоматически через ВКонтакте — до 15 запросов в день после авторизации",
    "userText": "До 15 запросов к ИИ в день",
    "quotaGuest": "Лимит: 5 запросов в день",
    "quotaUser": "Лимит: 15 запросов в день",
    "linking": "Подключаем аккаунт VK…",
    "linkFailed": "Не удалось подтвердить сессию VK. Закройте мини-приложение и откройте снова",
    "logout": "Выйти",
    "loggingOut": "Выходим…",
    "deleteAccount": "Удалить аккаунт",
    "deletingAccount": "Удаляем…",
    "deleteConfirm": "Удалить аккаунт Серпмонн и связанные данные? Это действие нельзя отменить.",
    "deleteFailed": "Не удалось удалить аккаунт. Попробуйте ещё раз",
    "deleteOk": "Аккаунт удалён"
  },
  "legal": {
    "privacyTitle": "Политика конфиденциальности",
    "privacyUrl": "/frontend/mini/privacy.html",
    "offerTitle": "Пользовательское соглашение",
    "offerUrl": "/frontend/mini/offer.html",
    "consentLabel": "Соглашаюсь с Политикой конфиденциальности и Пользовательским соглашением",
    "consentRequired": "Чтобы продолжить, отметьте согласие",
    "linksTitle": "Документы"
  },
  "search": {
    "placeholder": "Спросите ИИ что угодно…",
    "hint": "Ответ по интернету за несколько секунд",
    "submitAria": "Отправить запрос",
    "copy": "Копировать ответ",
    "share": "Поделиться",
    "copied": "Ответ скопирован",
    "copyFailed": "Не удалось скопировать",
    "shareFailed": "Не удалось поделиться",
    "like": "Ответ помог",
    "dislike": "Ответ не помог"
  },
  "auth": {
    "login": "Повторить вход",
    "loginHint": "Авторизация через vk_user_id (launch params)",
    "loggingIn": "Входим…",
    "loggedIn": "Вы вошли",
    "loginFailed": "Не удалось войти автоматически. Откройте мини-приложение снова из ВКонтакте",
    "guestQuota": "Гость · 5 запросов в день",
    "userQuota": "15 запросов в день",
    "statusGuest": "Гость · 5/день",
    "statusUser": "Вы вошли · 15/день"
  },
  "limit": {
    "guestTitle": "Лимит на сегодня закончился",
    "guestText": "Для большего лимита нужна сессия VK. Откройте мини-приложение снова — вход выполнится автоматически. Или загляните завтра.",
    "userTitle": "Лимит на сегодня закончился",
    "userText": "Завтра снова будет до 15 запросов. Пока можно открыть базу знаний, инструменты или поиграть.",
    "goNews": "База знаний",
    "goTools": "Инструменты",
    "goGames": "Игры",
    "retryAuth": "Повторить вход",
    "close": "Закрыть"
  },
  "news": {
    "title": "База знаний",
    "subtitle": "Статьи и материалы Серпмонн",
    "feedTitle": "Последние новости",
    "open": "Читать",
    "empty": "Пока нет материалов",
    "excludeLinkSubstrings": [
      "serpmonn-install-guide",
      "donate",
      "promo",
      "promocode",
      "snippet-limits",
      "telegram",
      "updates-",
      "updates_"
    ]
  },
  "tools": {
    "title": "Инструменты Серпмонн",
    "subtitle": "Калькуляторы и утилиты внутри приложения",
    "open": "Открыть",
    "items": [
      {
        "title": "Генератор UTM‑меток",
        "description": "UTM‑ссылки для рекламных кампаний",
        "href": "/frontend/tools/marketing/utm-builder.html"
      },
      {
        "title": "Счётчик слов",
        "description": "Подсчёт слов и символов в тексте",
        "href": "/frontend/tools/marketing/word-counter.html"
      },
      {
        "title": "Генератор паролей",
        "description": "Надёжные пароли за секунду",
        "href": "/frontend/tools/security/password-generator.html"
      },
      {
        "title": "JSON форматтер",
        "description": "Форматирование и проверка JSON",
        "href": "/frontend/tools/development/json-formatter.html"
      },
      {
        "title": "Base64 конвертер",
        "description": "Кодирование и декодирование Base64",
        "href": "/frontend/tools/development/base64-converter.html"
      },
      {
        "title": "Палитры цветов",
        "description": "Подбор и копирование цветов",
        "href": "/frontend/tools/design/color-palettes.html"
      },
      {
        "title": "Конвертер форматов",
        "description": "Быстрая конвертация данных",
        "href": "/frontend/tools/design/format-converter.html"
      },
      {
        "title": "Конвертер единиц",
        "description": "Перевод величин и единиц измерения",
        "href": "/frontend/tools/engineering/unit-converter.html"
      },
      {
        "title": "Калькулятор амортизации",
        "description": "Расчёт амортизации для логистики",
        "href": "/frontend/tools/logistics/depreciation-calculator.html"
      },
      {
        "title": "Калькулятор топлива",
        "description": "Расход и стоимость топлива",
        "href": "/frontend/tools/logistics/fuel-calculator.html"
      },
      {
        "title": "Эко‑след продукта",
        "description": "Оценка экологического следа",
        "href": "/frontend/tools/ecology/product-footprint-calculator.html"
      }
    ]
  },
  "games": {
    "title": "Игры Серпмонн",
    "subtitle": "Свои веб‑игры внутри приложения",
    "open": "Играть",
    "empty": "Скоро появятся новые игры"
  },
  "viewer": {
    "back": "Назад"
  },
  "onboarding": {
    "storageKey": "spn_vk_mini_onboarded_v5",
    "skip": "Пропустить",
    "next": "Далее",
    "done": "Начать",
    "slides": [
      {
        "title": "Добро пожаловать в Серпмонн",
        "text": "Агентный поиск с ИИ: задайте вопрос и получите ответ прямо во ВКонтакте."
      },
      {
        "title": "Что внутри",
        "text": "Умный поиск, база знаний, полезные инструменты и собственные мини‑игры — всё в одном приложении."
      },
      {
        "title": "Как пользоваться",
        "text": "Нижнее меню: Профиль, Поиск, База знаний, Инструменты и Игры."
      }
    ]
  },
  "cabinet": {
    "urls": [
      "https://serpmonn.ru/frontend/mini/miniapp.html"
    ],
    "note": "В кабинете VK для Mobile app, Desktop site, Mobile web и режимов разработки укажите один и тот же URL мини-приложения."
  }
}
